fastatomstruct-1.4.2.dist-info/METADATA
fastatomstruct-1.4.2.dist-info/WHEEL
fastatomstruct-1.4.2.dist-info/licenses/LICENSE
fastatomstruct/__init__.py
fastatomstruct/__init__.pyi
fastatomstruct/fastatomstruct.cpython-39-darwin.so
fastatomstruct/fastatomstruct.pyi
fastatomstruct-1.4.2.dist-info/RECORD
