Metadata-Version: 2.4
Name: fastatomstruct
Version: 1.4.2
Requires-Dist: ase
Requires-Dist: numpy
Requires-Dist: tidynamics
License-File: LICENSE
Summary: A Python package for the analysis of atomic structures and dynamics
Author: Nils Cedric Holle <nils.holle@uni-muenster.de>
Author-email: Nils Cedric Holle <nils.holle@uni-muenster.de>
License: GPL-3.0
